{"cameraMode":{"drawMode":0,"name":"Shaded","section":"Shading Mode"},"sceneLighting":false,"audioPlay":false,"sceneViewState":{"m_AlwaysRefresh":false,"showFog":true,"showSkybox":false,"showFlares":true,"showImageEffects":true,"showParticleSystems":true,"showVisualEffectGraphs":true,"m_FxEnabled":true},"in2DMode":false,"pivot":{"x":-3.106705665588379,"y":-3.394710063934326,"z":1.6230363845825196},"rotation":{"x":-0.3780477046966553,"y":-0.06879236549139023,"z":0.028163805603981019,"w":-0.9228278398513794},"size":4.521032810211182,"orthographic":false}